Workbook

Sheet Animal Register
A1: Field Name | B1: Animal Code | C1: Animal Type | D1: Breed | E1: Gender | F1: Date of Birth | G1: Age at Entry Weeks | H1: Entry Type | I1: Entry Date | J1: Source GRN | K1: Source Batch Born From | L1: Animal Item | M1: Serial Number | N1: RFID Tag | O1: Ear Tag Visual | P1: Sire Father | Q1: Dam Mother | R1: Acquisition Cost | S1: Landing Cost | T1: Total Opening Asset Value | U1: Current Stage | V1: Current Active Batch | W1: Current Location | X1: Parity Count | Y1: Total Piglets Born Live | Z1: Total Piglets Weaned | AA1: Current Bio Asset Value | AB1: Total Amortised | AC1: Book Value NBV | AD1: Residual Value | AE1: Monthly Amortisation | AF1: Productive Life Start Date | AG1: Expected Cull Date | AH1: Status | AI1: Disposal Date | AJ1: Disposal Type | AK1: Nos. of Teats | AL1: TSI | AM1: Grading | AN1: Bio Asset Value
A2: Description | B2: Auto-generated from No. Series ANIMAL_PIGGERY. Format: PIG-YYYY-SEQ. | C2: SOW / BOAR / GILT / PIGLET / COMMERCIAL_PIG | D2: Animal breed. Lookup from breed_master filtered by NOB and LOB. | E2: F = Female Sow or Gilt. M = Male Boar. | F2: Date of birth if born on this farm. NULL if imported and DOB unknown. | G2: Computed from dob and entry_date. Manual entry if imported and DOB unknown. | H2: PURCHASED_IMPORTED / PURCHASED_LOCAL / BORN_ON_FARM / TRANSFERRED_IN | I2: Date animal arrived or was born on this farm. | J2: GRN on which this animal arrived. Required if entry_type = PURCHASED. | K2: Farrowing batch that produced this animal. Required if entry_type = BORN_ON_FARM. | L2: Lookup to item_master for this animal type LIVING_ASSET. Links inventory and costing. | M2: Individual serial number from item_lot_serials. Created on GRN POST. | N2: RFID ear tag number for scanning. UNIQUE if set. | O2: Visual ear tag number. | P2: Father boar. Self-referential FK. Links to boar record. | Q2: Mother sow. Self-referential FK. | R2: Purchase price per animal. From PO line or manual entry on GRN. | S2: Transport import duty quarantine charges per head for imported animals. | T2: Total bio-asset value at entry. Auto-computed. | U2: QUARANTINE / GILT_GROWER / FLUSH / DRY_SOW / GESTATION / FARROWING / WEANING / PRODUCTIVE_SOW / BOAR_AI / CULLED / DEAD / SOLD / SLAUGHTERED | V2: FK to the batch this animal is currently in. | W2: FK to current shed or pen. | X2: Completed pregnancies. Incremented plus 1 on each weaning batch close. | Y2: Cumulative live births over lifetime. | Z2: Cumulative piglets weaned over lifetime. | AA2: Live biological asset value. Auto-updated from bio_asset_ledger. | AB2: Cumulative amortisation posted to date. | AC2: Net Book Value = Current Bio Asset Value minus Total Amortised. | AD2: Estimated salvage value at end of productive life. | AE2: Monthly amortisation charge. Auto-calculated. | AF2: Date animal entered productive stage first farrowing or PRODUCTIVE_SOW status. | AG2: Expected disposal date based on productive life. | AH2: ACTIVE / QUARANTINE / SICK / PREGNANT / LACTATING / DRY / CULLED / DEAD / SOLD / SLAUGHTERED | AI2: Date of sale slaughter or death. | AJ2: SOLD / SLAUGHTERED / DIED / TRANSFERRED | AK2: Count of Teates | AL2: Featched from Topigs | AM2: Flow from Navfarm Input (Back Fat - P2 measurement) | AN2: Non Current Asset/Flow from from BC | AO2: =+'[1]Imported Pigs Costing 0826'!$AX$6 -> Porta Total Cost | AP2: =+'[1]Imported Pigs Costing 0826'!BK$6 -> Current month Amortisation | AQ2: =+'[1]Imported Pigs Costing 0826'!BL$6 -> Residual Value | AR2: =+'[1]Imported Pigs Costing 0826'!BM$6 -> Acc Amortisation | AS2: =+'[1]Imported Pigs Costing 0826'!BN$6 -> NBV | AT2: =+'[1]Imported Pigs Costing 0826'!BO$6 -> 0
A3: Example Value | B3: PIG-2025-0001 | C3: SOW | D3: uuid-breed-01 | E3: F | F3: 2024-10-01 | G3: 3 | H3: PURCHASED_IMPORTED | I3: 2025-01-15 | J3: uuid-grn-001 | K3: uuid-batch-farr-001 | L3: uuid-item-gilt | M3: uuid-ls-001 | N3: RFID-PIG-001234 | O3: ET-2025-001 | P3: uuid-ani-boar-001 | Q3: uuid-ani-sow-001 | R3: 2857.5700 | S3: 200.0000 | T3: 3057.5700 | U3: QUARANTINE | V3: uuid-batch-gest-001 | W3: uuid-loc-pen-01a | X3: 2 | Y3: 23 | Z3: 21 | AA3: 3843.5700 | AB3: 200.0000 | AC3: 3643.5700 | AD3: 305.7600 | AE3: 84.9400 | AF3: 2025-08-01 | AG3: 2028-08-01 | AH3: ACTIVE | AI3: 2028-09-01 | AJ3: SOLD | AK3: 16 | AL3: 112 | AN3: 2223
A4: Mandatory | B4: YES | C4: YES | D4: YES | E4: YES | F4: NO | G4: NO | H4: YES | I4: YES | J4: COND | K4: COND | L4: YES | M4: YES | N4: NO | O4: NO | P4: NO | Q4: NO | R4: YES | S4: NO | T4: YES | U4: YES | V4: NO | W4: NO | X4: YES | Y4: YES | Z4: YES | AA4: YES | AB4: YES | AC4: YES | AD4: NO | AE4: NO | AF4: NO | AG4: NO | AH4: YES | AI4: COND | AJ4: COND | AK4: Yes | AL4: Yes | AM4: Yes | AN4: Yes
B6: DLNA8228 | C6: Sow | D6: TN70 | E6: F | F6: 45209 | G6: =+F6+120 -> 45329 | H6: Imported | I6: =+G6 -> 45329 | J6: N/A | K6: Directly Imported for Farm | L6: Living asset | M6: =+B6 -> DLNA8228 | N6: n/a | O6: =+M6 -> DLNA8228 | P6: N/A | Q6: NB6471 | R6: =+AO6 -> 392.82641 | S6: 0 | T6: =+R6+S6 -> 392.82641 | U6: PRODUCTIVE SOW | V6: WEEK 32 | W6: DRY SOW | X6: 5 | Y6: =+X6*16 -> 80 | Z6: 61 | AA6: =+AC6 -> 79.326414 | AB6: =+AQ6 -> 313.5 | AC6: =+T6-AB6 -> 79.326414 | AD6: =+AC6 -> 79.326414 | AE6: =+AD6 -> 79.326414 | AF6: =+F6+(47*7) -> 45538 | AG6: =+AF6+(365*5) -> 47363 | AH6: LACTATING | AI6: Date of disposal | AK6: 14 | AL6: 102 | AM6: 12 | AN6: =+AA6 -> 79.326414 | AO6: =SUM('[1]Imported Pigs Costing 0826'!$AX$128:$AX$132)/SUM('[1]Imported Pigs Costing 0826'!$X$128:$X$132) -> 392.82641 | AP6: =SUM('[1]Imported Pigs Costing 0826'!BK$128:BK$132)/SUM('[1]Imported Pigs Costing 0826'!$X$128:$X$132) -> 2.0340106 | AQ6: =SUM('[1]Imported Pigs Costing 0826'!BL$128:BL$132)/SUM('[1]Imported Pigs Costing 0826'!$X$128:$X$132) -> 313.5 | AR6: =SUM('[1]Imported Pigs Costing 0826'!BM$128:BM$132)/SUM('[1]Imported Pigs Costing 0826'!$X$128:$X$132) -> 46.922944 | AS6: =SUM('[1]Imported Pigs Costing 0826'!BN$128:BN$132)/SUM('[1]Imported Pigs Costing 0826'!$X$128:$X$132) -> 345.90347 | AT6: 45413
K7: get from Multiplier | L7: Living asset | R7: =+AO7 -> 0 | S7: 0 | T7: =+R7+S7 -> 0 | AA7: =+AC7 -> 0 | AB7: =+AQ7 -> 0 | AC7: =+T7-AB7 -> 0 | AD7: =+AC7 -> 0 | AE7: =+AD7 -> 0 | AN7: =+AA7 -> 0
B8: P26302 | C8: Gilt | D8: TN70 | E8: F | F8: 46026 | G8: =+F8+(10*7) -> 46096 | H8: Purchased local | I8: =+F8+28 -> 46054 | J8: N/A | K8: get from Multiplier | L8: Living Asset | M8: =+B8 -> P26302 | O8: =+M8 -> P26302 | P8: N/A | Q8: CU3647 | R8: =+AO8 -> 0 | S8: 0 | T8: =+R8+S8 -> 0 | U8: Gestation | V8: Week 26 | W8: Dry Sow | X8: 0 | Y8: 0 | Z8: 0 | AA8: =2.05*150 -> 307.5 | AB8: =+AQ8 -> 0 | AC8: =+T8-AB8 -> 0 | AD8: =+AC8 -> 0 | AE8: =+AD8 -> 0 | AF8: =+F8+(47*7) -> 46355 | AG8: =+AF8+(365*5) -> 48180 | AH8: Pregnant | AI8: Date | AK8: 16 | AL8: 106 | AM8: 14 | AN8: =+AA8 -> 307.5
R9: =+AO9 -> 0 | S9: 0 | T9: =+R9+S9 -> 0 | AA9: =+AC9 -> 0 | AB9: =+AQ9 -> 0 | AC9: =+T9-AB9 -> 0 | AD9: =+AC9 -> 0 | AE9: =+AD9 -> 0 | AN9: =+AA9 -> 0
B10: P25003 | C10: Gilt | D10: TN70 | E10: F | F10: 45968 | G10: =+F10+(10*7) -> 46038 | H10: Purchased local | I10: =+F10+28 -> 45996 | J10: N/A | K10: get from Multiplier | L10: Living Asset | M10: =+B10 -> P25003 | N10: n/a | O10: =+M10 -> P25003 | P10: N/A | Q10: CU3649 | R10: =+AO10 -> 0 | S10: 0 | T10: =+R10+S10 -> 0 | U10: Gestation | V10: Week 20 | W10: DRY SOW | X10: 0 | Y10: 0 | Z10: 0 | AA10: =+AA8 -> 307.5 | AB10: =+AQ10 -> 0 | AC10: =+T10-AB10 -> 0 | AD10: =+AC10 -> 0 | AE10: =+AD10 -> 0 | AF10: =+F10+(47*7) -> 46297 | AG10: =+AF10+(365*5) -> 48122 | AH10: Pregnant | AI10: Actual Date | AK10: 17 | AL10: 112 | AM10: 14 | AN10: =+AA10 -> 307.5
R11: =+AO11 -> 0 | S11: 0 | T11: =+R11+S11 -> 0 | AA11: =+AC11 -> 0 | AB11: =+AQ11 -> 0 | AC11: =+T11-AB11 -> 0 | AD11: =+AC11 -> 0 | AE11: =+AD11 -> 0 | AN11: =+AA11 -> 0
B12: P2975 | C12: Gilt | D12: TN70 | E12: F | F12: 45917 | G12: =+F12+(10*7) -> 45987 | H12: Purchased local | I12: =+F12+28 -> 45945 | J12: N/A | K12: get from Multiplier | L12: Living Asset | M12: =+B12 -> P2975 | N12: n/a | O12: =+M12 -> P2975 | P12: N/A | Q12: Get from Multiplier | R12: =+AO12 -> 0 | S12: 0 | T12: =+R12+S12 -> 0 | U12: WEANING | V12: WEEK 32 | W12: FARROWING | X12: 1 | Y12: 16 | AA12: =+AA10 -> 307.5 | AB12: =+AQ12 -> 0 | AC12: =+T12-AB12 -> 0 | AD12: =+AC12 -> 0 | AE12: =+AD12 -> 0 | AF12: =+F12+(47*7) -> 46246 | AG12: =+AF12+(365*5) -> 48071 | AH12: LACTATING | AI12: N/A | AK12: 15 | AL12: 102 | AM12: 14 | AN12: =+AA12 -> 307.5
R13: =+AO13 -> 0 | S13: 0 | T13: =+R13+S13 -> 0 | AA13: =+AC13 -> 0 | AB13: =+AQ13 -> 0 | AC13: =+T13-AB13 -> 0 | AD13: =+AC13 -> 0 | AE13: =+AD13 -> 0 | AN13: =+AA13 -> 0
B14: NB0552 | C14: SOW | D14: TN70 | E14: F | F14: 45209 | G14: =+F14+120 -> 45329 | H14: Imported | I14: =+G14 -> 45329 | J14: N/A | K14: Directly Imported for Farm | L14: Living asset | M14: =+B14 -> NB0552 | N14: n/a | O14: =+M14 -> NB0552 | P14: N/A | Q14: NB6471 | R14: =+AO14 -> 392.82641 | S14: 0 | T14: =+R14+S14 -> 392.82641 | U14: PRODUCTIVE SOW | V14: WEEK 33 | W14: DRY SOW | X14: 5 | Y14: 86 | Z14: =+X14*16 -> 80 | AA14: =+AC14 -> 79.326414 | AB14: =+AQ14 -> 313.5 | AC14: =+T14-AB14 -> 79.326414 | AD14: =+AC14 -> 79.326414 | AE14: =+AD14 -> 79.326414 | AF14: =+F14+(47*7) -> 45538 | AG14: =+AF14+(365*8) -> 48458 | AH14: PREGNANT | AI14: Date of disposal | AK14: 14 | AL14: 102 | AM14: 12 | AN14: =+AA14 -> 79.326414 | AO14: =+AO6 -> 392.82641 | AP14: =+AP6 -> 2.0340106 | AQ14: =+AQ6 -> 313.5 | AR14: =+AR6 -> 46.922944 | AS14: =+AS6 -> 345.90347 | AT14: =+AT6 -> 45413
A18: APPROVAL SECTION
A20: Compiled By:
A22: Reviewed and Approved
B23: General Manager - Johan Odendaal
A25: Approved By:
B26: Chief Executive Officer - Ian Kennaird
A28: Date:

Sheet Sheet1

Sheet  Breeding Record
A1: Breeding Record - AI or mating event per sow with semen lot pregnancy check and expected farrowing date, Just req data for the understanding, later stage.
A2: Field Name | B2: Tag Number | C2: Sow | D2: Batch | E2: Mating Type | F2: Boar | G2: Semen Lot | H2: Semen Dose Qty | I2: Mating Date | J2: Second Mating Date | K2: Expected Farrowing Date | L2: Pregnancy Check Date | M2: Pregnancy Check Method | N2: Pregnancy Confirmed | O2: Conception Result | P2: Parity Number
A3: Description | B3: Tag Number | C3: The sow being mated. Lookup from animal_register where animal_type = SOW or GILT. | D3: The Flush or AI batch containing this event. | E3: AI = Artificial Insemination. NATURAL_MATING = with boar. | F3: The boar for NATURAL_MATING. Required if mating_type = NATURAL_MATING. | G3: Semen lot consumed for AI. Required if mating_type = AI. FIFO consumption of semen inventory. | H3: Doses used for this insemination. Posted as CONSUMPTION to inventory_ledger. | I3: Date of insemination or natural mating. | J3: Follow-up insemination 48hr repeat for AI. | K3: Expected farrowing date. Auto-calculated. | L3: Date of pregnancy confirmation check. Typically 28 days post mating. | M3: ULTRASOUND / RECTAL / VISUAL / NOT_CHECKED | N3: NULL = pending. TRUE = confirmed. FALSE = failed. | O3: CONFIRMED / REPEAT / FAILED / PENDING. If FAILED sow returns to Flush. | P3: Which parity this is for this sow.
A4: Example Value | C4: uuid-ani-sow | D4: uuid-batch-flush | E4: AI | F4: uuid-ani-boar | G4: uuid-ls-semen | H4: 1.00 | I4: 2025-03-01 | J4: 2025-03-03 | K4: 2025-06-23 | L4: 2025-03-29 | M4: ULTRASOUND | N4: TRUE | O4: CONFIRMED | P4: 3
A5: Mandatory | B5: YES | C5: YES | D5: YES | E5: YES | F5: COND | G5: COND | H5: COND | I5: YES | J5: NO | K5: YES | L5: YES | M5: YES | N5: NO | O5: NO | P5: YES
B7: DLNA8228 | C7: Sow | E7: AI | F7: N/A | G7: T1 | H7: 2 | I7: 46219 | J7: =+I7+1 -> 46220 | K7: =+I7+116 -> 46335 | L7: =+I7+28 -> 46247 | M7: Ultrasound | N7: TRUE | O7: Confirmed | P7: 5
B9: =+'Animal Register'!B8 -> P26302 | C9: Gilt | E9: AI | F9: N/A | G9: T1 | H9: 1 | I9: =+'Animal Register'!F8+(31*7) -> 46243 | J9: n/a | K9: =+I9+116 -> 46359 | L9: =+I9+28 -> 46271 | M9: Ultrasound | N9: TRUE | O9: Confirmed | P9: 0
B11: =+'Animal Register'!B10 -> P25003 | C11: Gilt | E11: AI | F11: N/A | G11: T1 | H11: 1 | I11: =+'Animal Register'!F10+(31*7) -> 46185 | J11: n/a | K11: =+I11+116 -> 46301 | L11: =+I11+28 -> 46213 | M11: Ultrasound | N11: TRUE | O11: Confirmed | P11: 0
B13: =+'Animal Register'!B12 -> P2975 | C13: =+'Animal Register'!C12 -> Gilt | E13: AI | F13: N/A | G13: T2 | H13: 2 | I13: =+'Animal Register'!F12+(31*7) -> 46134 | J13: =+I13+1 -> 46135 | K13: =+I13+116 -> 46250 | L13: =+I13+28 -> 46162 | M13: Ultrasound | N13: TRUE | O13: Confirmed | P13: 1
B15: =+'Animal Register'!B14 -> NB0552 | C15: =+'Animal Register'!C14 -> SOW | E15: AI | F15: N/A | G15: T2 | H15: 2 | I15: 46244 | J15: =+I15+1 -> 46245 | K15: =+I15+116 -> 46360 | L15: =+I15+28 -> 46272 | M15: Ultrasound | N15: NULL | P15: 5
A19: APPROVAL SECTION
A21: Compiled By:
A23: Reviewed and Approved
B24: General Manager - Johan Odendaal
A26: Approved By:
B27: Chief Executive Officer - Ian Kennaird
A29: Date:
